Workbook

Sheet README
A1: Valuation workbook: Hindustan Unilever, Infosys, ICICI Bank
A3: Colour code
A4: Blue text = hardcoded input (each cites its source in the notes column)
A5: Black text = formula
A6: Green text = link pulled from another sheet
A7: Yellow fill = key assumption the group should review
A9: Sheets
A10: Inputs: market rates, company data and model assumptions. The only sheet you need to edit.
A11: DDM: two-stage dividend discount model for HUL and Infosys (BKM Ch 18).
A12: Bank: two-stage P/B (residual income) model for ICICI Bank; terminal value = book x justified P/B.
A13: Comps: peer multiples. Banks use P/B scaled by ROE because justified P/B rises with ROE.
A14: Sensitivity: intrinsic value across cost of equity (rows) and terminal growth (columns).
... A27: These models are very sensitive to r and g; read the Sensitivity sheet before quoting a single number.

Sheet Inputs
A1: Valuation inputs
A2: Edit blue cells and yellow assumptions only. Everything else is a formula.
A4: Market
A5: Risk-free rate (91-day T-bill) | B5: 0.055199 | E5: RBI, 91-day T-bill cut-off yield (auction of 30 Sep 2026); RBI homepage, as of 2026-10-01
A6: Equity risk premium (India, total) | B6: 0.0708 | E6: Damodaran, Country Default Spreads and Risk Premiums (India, Baa3), updated 2026-01-05
A7: Verdict band (+/- upside) | B7: 0.15 | E7: Assumption: blended upside beyond this = Under/Overvalued
A8: Price date | B8: 2026-10-01 | E8: NSE close via Yahoo Finance (pipeline data/latest)
A10: Company inputs | B10: Hindustan Unilever | C10: Infosys | D10: ICICI Bank | E10: Source / note
A11: Ticker | B11: HINDUNILVR.NS | C11: INFY.NS | D11: ICICIBANK.NS | E11: Yahoo Finance symbol
A12: Valuation model | B12: Two-stage DDM | C12: Two-stage DDM | D12: Two-stage P/B (residual income) | E12: Banks: free cash flow is not meaningful, so value book value x justified P/B
A13: Price (Rs) | B13: 1836 | C13: 1035 | D13: 1310.6 | E13: Pipeline data/latest/prices.parquet, last close
A14: Beta vs Nifty 50 | B14: 0.6004 | C14: 0.8211 | D14: 1.2949 | E14: Pipeline metrics.json: daily returns 2016 to price date
A15: Cost of equity r = rf + beta x ERP | B15: =$B$5+B14*$B$6 -> 0.09770732 | C15: =$B$5+C14*$B$6 -> 0.11333288 | D15: =$B$5+D14*$B$6 -> 0.14687792 | E15: CAPM (BKM Ch 9)
A16: Screener P/E (TTM, excl. exceptional items) | B16: 39.1 | C16: 13.5 | D16: 16.8 | E16: Screener.in public page, read 2 Oct 2026 (consolidated)
A17: EPS, TTM (Rs) = price / Screener P/E | B17: =B13/B16 -> 46.956522 | C17: =C13/C16 -> 76.666667 | D17: =D13/D16 -> 78.011905 | E17: Same earnings basis as the peer P/Es on the Comps sheet
A18: EPS FY21 (Rs) | B18: 34.03 | C18: 45.42 | D18: 26.58 | E18: Screener.in public page, read 2 Oct 2026 (consolidated), P&L table
A19: EPS growth, ~5-yr CAGR | B19: =(B17/B18)^(1/5)-1 -> 0.066514573 | C19: =(C17/C18)^(1/5)-1 -> 0.11038066 | D19: =(D17/D18)^(1/5)-1 -> 0.24028411 | E19: FY21 to TTM; a reference point for g1, not used directly
A20: Dividend per share FY26 = D0 (Rs) | B20: 41 | C20: 48 | D20: 12 | E20: Yahoo Finance dividends: HUL 19 (Nov-25) + 22 (Jun-26); INFY 23 (Oct-25) + 25 (Jun-26); ICICI 12 (Aug-26)
A21: Payout ratio (DPS / EPS TTM) | B21: =B20/B17 -> 0.87314815 | C21: =C20/C17 -> 0.62608696 | D21: =D20/D17 -> 0.15382268
A22: Book value per share (Rs) | B22: 207 | C22: 225 | D22: 527 | E22: Screener.in public page, read 2 Oct 2026 (consolidated)
A23: ROE, latest FY | B23: 0.31 | C23: 0.319 | D23: 0.159 | E23: Screener.in public page, read 2 Oct 2026 (consolidated) (HUL's figure includes the FY26 one-off gain)
A25: Model assumptions (review these)
A26: High-growth years N (1 to 10) | B26: 5 | C26: 5 | D26: 5 | E26: Assumption: same horizon for all three for comparability
A27: Dividend growth in high-growth phase g1 (DDM) | B27: 0.07 | C27: 0.08 | D27: n/a | E27: Assumption. HUL: ~5-yr sales CAGR 6.5-7% with flat margins. INFY: between 5-yr EPS CAGR (~10%) and 3-yr profit growth (8%)
A28: ROE in high-growth phase (bank) | B28: n/a | C28: n/a | D28: 0.16 | E28: Assumption: FY26 ROE held for N years (3-yr average was 17%)
A29: Payout in high-growth phase (bank) | B29: n/a | C29: n/a | D29: 0.16 | E29: Assumption: FY26 payout per Screener (16%)
A30: Stable ROE after year N (bank) | B30: n/a | C30: n/a | D30: 0.15 | E30: Assumption: ROE fades toward the peer range (11-14%) but stays above it
A31: Terminal growth g2 (keep at or below rf) | B31: 0.055 | C31: 0.055 | D31: 0.055 | E31: Assumption: capped at rf, a proxy for long-run nominal growth
A32: Check: g2 at or below rf | B32: =IF(B31<=$B$5,"OK","g2 above rf") -> OK | C32: =IF(C31<=$B$5,"OK","g2 above rf") -> OK | D32: =IF(D31<=$B$5,"OK","g2 above rf") -> OK
A33: Check: g2 below r | B33: =IF(B31<B15,"OK","g2 must be below r") -> OK | C33: =IF(C31<C15,"OK","g2 must be below r") -> OK | D33: =IF(D31<D15,"OK","g2 must be below r") -> OK

Sheet DDM
A1: Two-stage dividend discount model: Hindustan Unilever and Infosys
A2: Dividends grow at g1 for N years, then at g2 for ever. Value = PV of dividends in years 1-10 + PV of the terminal value at year 10. Years after N already grow at g2, so any N from 1 to 10 gives the textbook two-stage value.
A4: Inputs (linked) | B4: Hindustan Unilever | C4: Infosys
A5: D0, dividend just paid (Rs) | B5: =Inputs!B20 -> 41 | C5: =Inputs!C20 -> 48
A6: Cost of equity r | B6: =Inputs!B15 -> 0.09770732 | C6: =Inputs!C15 -> 0.11333288
A7: High-growth rate g1 | B7: =Inputs!B27 -> 0.07 | C7: =Inputs!C27 -> 0.08
A8: High-growth years N | B8: =Inputs!B26 -> 5 | C8: =Inputs!C26 -> 5
A9: Terminal growth g2 | B9: =Inputs!B31 -> 0.055 | C9: =Inputs!C31 -> 0.055
A10: Market price (Rs) | B10: =Inputs!B13 -> 1836 | C10: =Inputs!C13 -> 1035
A12: Year | B12: HUL growth | C12: HUL dividend (Rs) | D12: HUL PV (Rs) | E12: INFY growth | F12: INFY dividend (Rs) | G12: INFY PV (Rs)
A13: 0 | C13: =B5 -> 41 | F13: =C5 -> 48
A14: 1 | B14: =IF(A14<=$B$8,$B$7,$B$9) -> 0.07 | C14: =C13*(1+B14) -> 43.87 | D14: =C14/(1+$B$6)^A14 -> 39.965116 | E14: =IF(A14<=$C$8,$C$7,$C$9) -> 0.08 | F14: =F13*(1+E14) -> 51.84 | G14: =F14/(1+$C$6)^A14 -> 46.562893
A15: 2 | B15: =IF(A15<=$B$8,$B$7,$B$9) -> 0.07 | C15: =C14*(1+B15) -> 46.9409 | D15: =C15/(1+$B$6)^A15 -> 38.956353 | E15: =IF(A15<=$C$8,$C$7,$C$9) -> 0.08 | F15: =F14*(1+E15) -> 55.9872 | G15: =F15/(1+$C$6)^A15 -> 45.168813
A16: 3 | B16: =IF(A16<=$B$8,$B$7,$B$9) -> 0.07 | C16: =C15*(1+B16) -> 50.226763 | D16: =C16/(1+$B$6)^A16 -> 37.973052 | E16: =IF(A16<=$C$8,$C$7,$C$9) -> 0.08 | F16: =F15*(1+E16) -> 60.466176 | G16: =F16/(1+$C$6)^A16 -> 43.816471
A17: 4 | B17: =IF(A17<=$B$8,$B$7,$B$9) -> 0.07 | C17: =C16*(1+B17) -> 53.742636 | D17: =C17/(1+$B$6)^A17 -> 37.014572 | E17: =IF(A17<=$C$8,$C$7,$C$9) -> 0.08 | F17: =F16*(1+E17) -> 65.30347 | G17: =F17/(1+$C$6)^A17 -> 42.504618
A18: 5 | B18: =IF(A18<=$B$8,$B$7,$B$9) -> 0.07 | C18: =C17*(1+B18) -> 57.504621 | D18: =C18/(1+$B$6)^A18 -> 36.080284 | E18: =IF(A18<=$C$8,$C$7,$C$9) -> 0.08 | F18: =F17*(1+E18) -> 70.527748 | G18: =F18/(1+$C$6)^A18 -> 41.232042
A19: 6 | B19: =IF(A19<=$B$8,$B$7,$B$9) -> 0.055 | C19: =C18*(1+B19) -> 60.667375 | D19: =C19/(1+$B$6)^A19 -> 34.676547 | E19: =IF(A19<=$C$8,$C$7,$C$9) -> 0.055 | F19: =F18*(1+E19) -> 74.406774 | G19: =F19/(1+$C$6)^A19 -> 39.071696
A20: 7 | B20: =IF(A20<=$B$8,$B$7,$B$9) -> 0.055 | C20: =C19*(1+B20) -> 64.004081 | D20: =C20/(1+$B$6)^A20 -> 33.327424 | E20: =IF(A20<=$C$8,$C$7,$C$9) -> 0.055 | F20: =F19*(1+E20) -> 78.499146 | G20: =F20/(1+$C$6)^A20 -> 37.024541
A21: 8 | B21: =IF(A21<=$B$8,$B$7,$B$9) -> 0.055 | C21: =C20*(1+B21) -> 67.524305 | D21: =C21/(1+$B$6)^A21 -> 32.030789 | E21: =IF(A21<=$C$8,$C$7,$C$9) -> 0.055 | F21: =F20*(1+E21) -> 82.816599 | G21: =F21/(1+$C$6)^A21 -> 35.084647
A22: 9 | B22: =IF(A22<=$B$8,$B$7,$B$9) -> 0.055 | C22: =C21*(1+B22) -> 71.238142 | D22: =C22/(1+$B$6)^A22 -> 30.784602 | E22: =IF(A22<=$C$8,$C$7,$C$9) -> 0.055 | F22: =F21*(1+E22) -> 87.371512 | G22: =F22/(1+$C$6)^A22 -> 33.246393
A23: 10 | B23: =IF(A23<=$B$8,$B$7,$B$9) -> 0.055 | C23: =C22*(1+B23) -> 75.15624 | D23: =C23/(1+$B$6)^A23 -> 29.586898 | E23: =IF(A23<=$C$8,$C$7,$C$9) -> 0.055 | F23: =F22*(1+E23) -> 92.176946 | G23: =F23/(1+$C$6)^A23 -> 31.504454
A25: Results | B25: Hindustan Unilever | C25: Infosys
A26: PV of dividends, years 1-10 (Rs) | B26: =SUM(D14:D23) -> 350.39564 | C26: =SUM(G14:G23) -> 395.21657
A27: Terminal value at year 10 (Rs) | B27: =C23*(1+B9)/(B6-B9) -> 1856.5865 | C27: =F23*(1+C9)/(C6-C9) -> 1667.0989
A28: PV of terminal value (Rs) | B28: =B27/(1+B6)^10 -> 730.8859 | C28: =C27/(1+C6)^10 -> 569.78499
A29: Intrinsic value per share (Rs) | B29: =B26+B28 -> 1081.2815 | C29: =C26+C28 -> 965.00155
A30: Market price (Rs) | B30: =B10 -> 1836 | C30: =C10 -> 1035
A31: Upside (intrinsic / price - 1) | B31: =B29/B30-1 -> -0.4110667 | C31: =C29/C30-1 -> -0.067631348
A32: Share of value from terminal value | B32: =B28/B29 -> 0.67594412 | C32: =C28/C29 -> 0.59044981
A33: Market-implied perpetual growth (reverse DDM) | B33: =(B6*B30-B5)/(B30+B5) -> 0.073729696 | C33: =(C6*C30-C5)/(C30+C5) -> 0.063988486
A34: Check: closed-form two-stage value (Rs) | B34: =B5*(1+B7)/(B6-B7)*(1-((1+B7)/(1+B6))^B8)+B5*(1+B7)^B8*(1+B9)/((B6-B9)*(1+B6)^B8) -> 1081.2815 | C34: =C5*(1+C7)/(C6-C7)*(1-((1+C7)/(1+C6))^C8)+C5*(1+C7)^C8*(1+C9)/((C6-C9)*(1+C6)^C8) -> 965.00155
A35: Check: table minus closed form (should be 0) | B35: =ROUND(B29-B34,6) -> 0 | C35: =ROUND(C29-C34,6) -> 0
A36: Reverse DDM: the constant growth g at which Gordon's formula D0(1+g)/(r-g) equals today's price, i.e. g = (r x P - D0) / (P + D0).

Sheet Bank
A1: ICICI Bank: two-stage P/B (residual income) model
A2: Book value compounds at ROE x retention. For N years the bank keeps its current ROE and payout; afterwards payout = 1 - g2/ROE, just enough retention to grow book at g2. Terminal value = book value x justified P/B, where justified P/B = (ROE - g) / (r - g).
A4: Inputs (linked) | B4: ICICI Bank
A5: Book value per share now (Rs) | B5: =Inputs!D22 -> 527
A6: Cost of equity r | B6: =Inputs!D15 -> 0.14687792
A7: High-growth years N | B7: =Inputs!D26 -> 5
A8: ROE in high-growth phase | B8: =Inputs!D28 -> 0.16
A9: Payout in high-growth phase | B9: =Inputs!D29 -> 0.16
A10: Stable ROE after year N | B10: =Inputs!D30 -> 0.15
A11: Terminal growth g2 | B11: =Inputs!D31 -> 0.055
A12: Market price (Rs) | B12: =Inputs!D13 -> 1310.6
A13: Stable payout = 1 - g2 / stable ROE | B13: =1-B11/B10 -> 0.63333333
A15: Year | B15: Opening book (Rs) | C15: ROE | D15: EPS (Rs) | E15: Payout | F15: DPS (Rs) | G15: Closing book (Rs) | H15: PV of DPS (Rs)
A16: 1 | B16: =$B$5 -> 527 | C16: =IF(A16<=$B$7,$B$8,$B$10) -> 0.16 | D16: =B16*C16 -> 84.32 | E16: =IF(A16<=$B$7,$B$9,$B$13) -> 0.16 | F16: =D16*E16 -> 13.4912 | G16: =B16+D16-F16 -> 597.8288 | H16: =F16/(1+$B$6)^A16 -> 11.763414
A17: 2 | B17: =G16 -> 597.8288 | C17: =IF(A17<=$B$7,$B$8,$B$10) -> 0.16 | D17: =B17*C17 -> 95.652608 | E17: =IF(A17<=$B$7,$B$9,$B$13) -> 0.16 | F17: =D17*E17 -> 15.304417 | G17: =B17+D17-F17 -> 678.17699 | H17: =F17/(1+$B$6)^A17 -> 11.635429
A18: 3 | B18: =G17 -> 678.17699 | C18: =IF(A18<=$B$7,$B$8,$B$10) -> 0.16 | D18: =B18*C18 -> 108.50832 | E18: =IF(A18<=$B$7,$B$9,$B$13) -> 0.16 | F18: =D18*E18 -> 17.361331 | G18: =B18+D18-F18 -> 769.32398 | H18: =F18/(1+$B$6)^A18 -> 11.508837
A19: 4 | B19: =G18 -> 769.32398 | C19: =IF(A19<=$B$7,$B$8,$B$10) -> 0.16 | D19: =B19*C19 -> 123.09184 | E19: =IF(A19<=$B$7,$B$9,$B$13) -> 0.16 | F19: =D19*E19 -> 19.694694 | G19: =B19+D19-F19 -> 872.72112 | H19: =F19/(1+$B$6)^A19 -> 11.383622
A20: 5 | B20: =G19 -> 872.72112 | C20: =IF(A20<=$B$7,$B$8,$B$10) -> 0.16 | D20: =B20*C20 -> 139.63538 | E20: =IF(A20<=$B$7,$B$9,$B$13) -> 0.16 | F20: =D20*E20 -> 22.341661 | G20: =B20+D20-F20 -> 990.01484 | H20: =F20/(1+$B$6)^A20 -> 11.259769
A21: 6 | B21: =G20 -> 990.01484 | C21: =IF(A21<=$B$7,$B$8,$B$10) -> 0.15 | D21: =B21*C21 -> 148.50223 | E21: =IF(A21<=$B$7,$B$9,$B$13) -> 0.63333333 | F21: =D21*E21 -> 94.05141 | G21: =B21+D21-F21 -> 1044.4657 | H21: =F21/(1+$B$6)^A21 -> 41.329691
A22: 7 | B22: =G21 -> 1044.4657 | C22: =IF(A22<=$B$7,$B$8,$B$10) -> 0.15 | D22: =B22*C22 -> 156.66985 | E22: =IF(A22<=$B$7,$B$9,$B$13) -> 0.63333333 | F22: =D22*E22 -> 99.224237 | G22: =B22+D22-F22 -> 1101.9113 | H22: =F22/(1+$B$6)^A22 -> 38.018714
A23: 8 | B23: =G22 -> 1101.9113 | C23: =IF(A23<=$B$7,$B$8,$B$10) -> 0.15 | D23: =B23*C23 -> 165.28669 | E23: =IF(A23<=$B$7,$B$9,$B$13) -> 0.63333333 | F23: =D23*E23 -> 104.68157 | G23: =B23+D23-F23 -> 1162.5164 | H23: =F23/(1+$B$6)^A23 -> 34.972985
A24: 9 | B24: =G23 -> 1162.5164 | C24: =IF(A24<=$B$7,$B$8,$B$10) -> 0.15 | D24: =B24*C24 -> 174.37746 | E24: =IF(A24<=$B$7,$B$9,$B$13) -> 0.63333333 | F24: =D24*E24 -> 110.43906 | G24: =B24+D24-F24 -> 1226.4548 | H24: =F24/(1+$B$6)^A24 -> 32.171252
A25: 10 | B25: =G24 -> 1226.4548 | C25: =IF(A25<=$B$7,$B$8,$B$10) -> 0.15 | D25: =B25*C25 -> 183.96822 | E25: =IF(A25<=$B$7,$B$9,$B$13) -> 0.63333333 | F25: =D25*E25 -> 116.5132 | G25: =B25+D25-F25 -> 1293.9098 | H25: =F25/(1+$B$6)^A25 -> 29.59397
A27: Results | B27: ICICI Bank
A28: PV of dividends, years 1-10 (Rs) | B28: =SUM(H16:H25) -> 233.63768
A29: Justified P/B at year 10 = (ROE - g2) / (r - g2) | B29: =(B10-B11)/(B6-B11) -> 1.0339807
A30: Terminal value = book at year 10 x justified P/B (Rs) | B30: =G25*B29 -> 1337.8778
A31: PV of terminal value (Rs) | B31: =B30/(1+B6)^10 -> 339.81656
A32: Intrinsic value per share (Rs) | B32: =B28+B31 -> 573.45424
A33: Market price (Rs) | B33: =B12 -> 1310.6
A34: Upside (intrinsic / price - 1) | B34: =B32/B33-1 -> -0.56244908
A35: Intrinsic P/B (intrinsic / book now) | B35: =B32/B5 -> 1.0881485
A36: Market P/B (price / book now) | B36: =B33/B5 -> 2.486907
A37: Market-implied perpetual growth at today's ROE | B37: =(B6*B36-Inputs!D23)/(B36-1) -> 0.13872537
A38: Check: closed-form value (Rs) | B38: =B9*B8*B5/(B6-B8*(1-B9))*(1-((1+B8*(1-B9))/(1+B6))^B7)+B5*(1+B8*(1-B9))^B7*(B10-B11)/(B6-B11)/(1+B6)^B7 -> 573.45424
A39: Check: table minus closed form (should be 0) | B39: =ROUND(B32-B38,6) -> 0
A40: Implied growth solves single-stage P/B = (ROE - g) / (r - g) for g: g = (r x P/B - ROE) / (P/B - 1).

Sheet Comps
A1: Peer multiples
A2: Peer figures: Screener.in public page, read 2 Oct 2026 (consolidated). P/E is Screener's TTM P/E.
A4: FMCG peers for Hindustan Unilever
A5: Peer | B5: P/E (TTM) | C5: Price (Rs)
A6: Nestle India | B6: 68 | C6: 1308
A7: Britannia Industries | B7: 44.2 | C7: 4778
A8: Dabur India | B8: 33.5 | C8: 374
A9: Median peer P/E | B9: =MEDIAN(B6:B8) -> 44.2
A10: HUL EPS, TTM (Rs) | B10: =Inputs!B17 -> 46.956522
A11: HUL value at median P/E (Rs) | B11: =B9*B10 -> 2075.4783
A13: IT services peers for Infosys
A14: Peer | B14: P/E (TTM) | C14: Price (Rs)
A15: TCS | B15: 14 | C15: 2075
A16: HCL Technologies | B16: 18.6 | C16: 1243
A17: Wipro | B17: 11.9 | C17: 159
A18: Median peer P/E | B18: =MEDIAN(B15:B17) -> 14
A19: Infosys EPS, TTM (Rs) | B19: =Inputs!C17 -> 76.666667
A20: Infosys value at median P/E (Rs) | B20: =B18*B19 -> 1073.3333
A22: Private bank peers for ICICI Bank
A23: Peer | B23: P/E (TTM) | C23: Price (Rs) | D23: Book value (Rs) | E23: ROE | F23: P/B | G23: P/B per unit of ROE
A24: HDFC Bank | B24: 14.1 | C24: 721 | D24: 390 | E24: 0.136 | F24: =C24/D24 -> 1.8487179 | G24: =F24/E24 -> 13.593514
A25: Kotak Mahindra Bank | B25: 20.8 | C25: 418 | D25: 182 | E25: 0.114 | F25: =C25/D25 -> 2.2967033 | G25: =F25/E25 -> 20.14652
A26: Axis Bank | B26: 13.6 | C26: 1217 | D26: 712 | E26: 0.131 | F26: =C26/D26 -> 1.7092697 | G26: =F26/E26 -> 13.04786
A27: Median | B27: =MEDIAN(B24:B26) -> 14.1 | F27: =MEDIAN(F24:F26) -> 1.8487179 | G27: =MEDIAN(G24:G26) -> 13.593514
A28: ICICI Bank ROE (latest FY) | B28: =Inputs!D23 -> 0.159
A29: ICICI Bank book value per share (Rs) | B29: =Inputs!D22 -> 527
A30: ICICI value at median P/B (Rs), for reference | B30: =F27*B29 -> 974.27436
A31: ICICI value at ROE-adjusted median P/B (Rs) | B31: =G27*B28*B29 -> 1139.0413
A32: ROE-adjusted because justified P/B = (ROE - g)/(r - g) rises with ROE, and ICICI's ROE is above all three peers.

Sheet Sensitivity
A1: Intrinsic value (Rs) vs cost of equity and terminal growth
A2: Rows shift r from its CAPM base; columns shift g2 from its base. Other inputs as on Inputs. Bold cell = base case. Blank where g2 >= r (formula invalid).
A4: Hindustan Unilever (two-stage DDM)
A5: r \ g2 | B5: =Inputs!$B$31+(-0.015) -> 0.04 | C5: =Inputs!$B$31+(-0.01) -> 0.045 | D5: =Inputs!$B$31+(-0.005) -> 0.05 | E5: =Inputs!$B$31+(0) -> 0.055 | F5: =Inputs!$B$31+(0.005) -> 0.06
A6: =Inputs!$B$15+(-0.02) -> 0.07770732 | B6: =IF(B$5<$A6,Inputs!$B$20*(1+Inputs!$B$27)/($A6-Inputs!$B$27)*(1-((1+Inputs!$B$27)/(1+$A6))^Inputs!$B$26)+Inputs!$B$20*(1+Inputs!$B$27)^Inputs!$B$26*(1+B$5)/(($A6-B$5)*(1+$A6)^Inputs!$B$26),"") -> 1291.597 | C6: =IF(C$5<$A6,Inputs!$B$20*(1+Inputs!$B$27)/($A6-Inputs!$B$27)*(1-((1+Inputs!$B$27)/(1+$A6))^Inputs!$B$26)+Inputs!$B$20*(1+Inputs!$B$27)^Inputs!$B$26*(1+C$5)/(($A6-C$5)*(1+$A6)^Inputs!$B$26),"") -> 1464.4189 | D6: =IF(D$5<$A6,Inputs!$B$20*(1+Inputs!$B$27)/($A6-Inputs!$B$27)*(1-((1+Inputs!$B$27)/(1+$A6))^Inputs!$B$26)+Inputs!$B$20*(1+Inputs!$B$27)^Inputs!$B$26*(1+D$5)/(($A6-D$5)*(1+$A6)^Inputs!$B$26),"") -> 1699.6149 | E6: =IF(E$5<$A6,Inputs!$B$20*(1+Inputs!$B$27)/($A6-Inputs!$B$27)*(1-((1+Inputs!$B$27)/(1+$A6))^Inputs!$B$26)+Inputs!$B$20*(1+Inputs!$B$27)^Inputs!$B$26*(1+E$5)/(($A6-E$5)*(1+$A6)^Inputs!$B$26),"") -> 2038.3881 | F6: =IF(F$5<$A6,Inputs!$B$20*(1+Inputs!$B$27)/($A6-Inputs!$B$27)*(1-((1+Inputs!$B$27)/(1+$A6))^Inputs!$B$26)+Inputs!$B$20*(1+Inputs!$B$27)^Inputs!$B$26*(1+F$5)/(($A6-F$5)*(1+$A6)^Inputs!$B$26),"") -> 2568.4794
A7: =Inputs!$B$15+(-0.01) -> 0.08770732 | B7: =IF(B$5<$A7,Inputs!$B$20*(1+Inputs!$B$27)/($A7-Inputs!$B$27)*(1-((1+Inputs!$B$27)/(1+$A7))^Inputs!$B$26)+Inputs!$B$20*(1+Inputs!$B$27)^Inputs!$B$26*(1+B$5)/(($A7-B$5)*(1+$A7)^Inputs!$B$26),"") -> 1018.5648 | C7: =IF(C$5<$A7,Inputs!$B$20*(1+Inputs!$B$27)/($A7-Inputs!$B$27)*(1-((1+Inputs!$B$27)/(1+$A7))^Inputs!$B$26)+Inputs!$B$20*(1+Inputs!$B$27)^Inputs!$B$26*(1+C$5)/(($A7-C$5)*(1+$A7)^Inputs!$B$26),"") -> 1119.3826 | D7: =IF(D$5<$A7,Inputs!$B$20*(1+Inputs!$B$27)/($A7-Inputs!$B$27)*(1-((1+Inputs!$B$27)/(1+$A7))^Inputs!$B$26)+Inputs!$B$20*(1+Inputs!$B$27)^Inputs!$B$26*(1+D$5)/(($A7-D$5)*(1+$A7)^Inputs!$B$26),"") -> 1246.9373 | E7: =IF(E$5<$A7,Inputs!$B$20*(1+Inputs!$B$27)/($A7-Inputs!$B$27)*(1-((1+Inputs!$B$27)/(1+$A7))^Inputs!$B$26)+Inputs!$B$20*(1+Inputs!$B$27)^Inputs!$B$26*(1+E$5)/(($A7-E$5)*(1+$A7)^Inputs!$B$26),"") -> 1413.4909 | F7: =IF(F$5<$A7,Inputs!$B$20*(1+Inputs!$B$27)/($A7-Inputs!$B$27)*(1-((1+Inputs!$B$27)/(1+$A7))^Inputs!$B$26)+Inputs!$B$20*(1+Inputs!$B$27)^Inputs!$B$26*(1+F$5)/(($A7-F$5)*(1+$A7)^Inputs!$B$26),"") -> 1640.1562
A8: =Inputs!$B$15+(0) -> 0.09770732 | B8: =IF(B$5<$A8,Inputs!$B$20*(1+Inputs!$B$27)/($A8-Inputs!$B$27)*(1-((1+Inputs!$B$27)/(1+$A8))^Inputs!$B$26)+Inputs!$B$20*(1+Inputs!$B$27)^Inputs!$B$26*(1+B$5)/(($A8-B$5)*(1+$A8)^Inputs!$B$26),"") -> 840.22742 | C8: =IF(C$5<$A8,Inputs!$B$20*(1+Inputs!$B$27)/($A8-Inputs!$B$27)*(1-((1+Inputs!$B$27)/(1+$A8))^Inputs!$B$26)+Inputs!$B$20*(1+Inputs!$B$27)^Inputs!$B$26*(1+C$5)/(($A8-C$5)*(1+$A8)^Inputs!$B$26),"") -> 905.33397 | D8: =IF(D$5<$A8,Inputs!$B$20*(1+Inputs!$B$27)/($A8-Inputs!$B$27)*(1-((1+Inputs!$B$27)/(1+$A8))^Inputs!$B$26)+Inputs!$B$20*(1+Inputs!$B$27)^Inputs!$B$26*(1+D$5)/(($A8-D$5)*(1+$A8)^Inputs!$B$26),"") -> 984.0876 | E8: =IF(E$5<$A8,Inputs!$B$20*(1+Inputs!$B$27)/($A8-Inputs!$B$27)*(1-((1+Inputs!$B$27)/(1+$A8))^Inputs!$B$26)+Inputs!$B$20*(1+Inputs!$B$27)^Inputs!$B$26*(1+E$5)/(($A8-E$5)*(1+$A8)^Inputs!$B$26),"") -> 1081.2815 | F8: =IF(F$5<$A8,Inputs!$B$20*(1+Inputs!$B$27)/($A8-Inputs!$B$27)*(1-((1+Inputs!$B$27)/(1+$A8))^Inputs!$B$26)+Inputs!$B$20*(1+Inputs!$B$27)^Inputs!$B$26*(1+F$5)/(($A8-F$5)*(1+$A8)^Inputs!$B$26),"") -> 1204.2513
A9: =Inputs!$B$15+(0.01) -> 0.10770732 | B9: =IF(B$5<$A9,Inputs!$B$20*(1+Inputs!$B$27)/($A9-Inputs!$B$27)*(1-((1+Inputs!$B$27)/(1+$A9))^Inputs!$B$26)+Inputs!$B$20*(1+Inputs!$B$27)^Inputs!$B$26*(1+B$5)/(($A9-B$5)*(1+$A9)^Inputs!$B$26),"") -> 714.6245 | C9: =IF(C$5<$A9,Inputs!$B$20*(1+Inputs!$B$27)/($A9-Inputs!$B$27)*(1-((1+Inputs!$B$27)/(1+$A9))^Inputs!$B$26)+Inputs!$B$20*(1+Inputs!$B$27)^Inputs!$B$26*(1+C$5)/(($A9-C$5)*(1+$A9)^Inputs!$B$26),"") -> 759.60443 | D9: =IF(D$5<$A9,Inputs!$B$20*(1+Inputs!$B$27)/($A9-Inputs!$B$27)*(1-((1+Inputs!$B$27)/(1+$A9))^Inputs!$B$26)+Inputs!$B$20*(1+Inputs!$B$27)^Inputs!$B$26*(1+D$5)/(($A9-D$5)*(1+$A9)^Inputs!$B$26),"") -> 812.37885 | E9: =IF(E$5<$A9,Inputs!$B$20*(1+Inputs!$B$27)/($A9-Inputs!$B$27)*(1-((1+Inputs!$B$27)/(1+$A9))^Inputs!$B$26)+Inputs!$B$20*(1+Inputs!$B$27)^Inputs!$B$26*(1+E$5)/(($A9-E$5)*(1+$A9)^Inputs!$B$26),"") -> 875.16601 | F9: =IF(F$5<$A9,Inputs!$B$20*(1+Inputs!$B$27)/($A9-Inputs!$B$27)*(1-((1+Inputs!$B$27)/(1+$A9))^Inputs!$B$26)+Inputs!$B$20*(1+Inputs!$B$27)^Inputs!$B$26*(1+F$5)/(($A9-F$5)*(1+$A9)^Inputs!$B$26),"") -> 951.11407
A10: =Inputs!$B$15+(0.02) -> 0.11770732 | B10: =IF(B$5<$A10,Inputs!$B$20*(1+Inputs!$B$27)/($A10-Inputs!$B$27)*(1-((1+Inputs!$B$27)/(1+$A10))^Inputs!$B$26)+Inputs!$B$20*(1+Inputs!$B$27)^Inputs!$B$26*(1+B$5)/(($A10-B$5)*(1+$A10)^Inputs!$B$26),"") -> 621.39489 | C10: =IF(C$5<$A10,Inputs!$B$20*(1+Inputs!$B$27)/($A10-Inputs!$B$27)*(1-((1+Inputs!$B$27)/(1+$A10))^Inputs!$B$26)+Inputs!$B$20*(1+Inputs!$B$27)^Inputs!$B$26*(1+C$5)/(($A10-C$5)*(1+$A10)^Inputs!$B$26),"") -> 654.0026 | D10: =IF(D$5<$A10,Inputs!$B$20*(1+Inputs!$B$27)/($A10-Inputs!$B$27)*(1-((1+Inputs!$B$27)/(1+$A10))^Inputs!$B$26)+Inputs!$B$20*(1+Inputs!$B$27)^Inputs!$B$26*(1+D$5)/(($A10-D$5)*(1+$A10)^Inputs!$B$26),"") -> 691.42629 | E10: =IF(E$5<$A10,Inputs!$B$20*(1+Inputs!$B$27)/($A10-Inputs!$B$27)*(1-((1+Inputs!$B$27)/(1+$A10))^Inputs!$B$26)+Inputs!$B$20*(1+Inputs!$B$27)^Inputs!$B$26*(1+E$5)/(($A10-E$5)*(1+$A10)^Inputs!$B$26),"") -> 734.81797 | F10: =IF(F$5<$A10,Inputs!$B$20*(1+Inputs!$B$27)/($A10-Inputs!$B$27)*(1-((1+Inputs!$B$27)/(1+$A10))^Inputs!$B$26)+Inputs!$B$20*(1+Inputs!$B$27)^Inputs!$B$26*(1+F$5)/(($A10-F$5)*(1+$A10)^Inputs!$B$26),"") -> 785.72892
A11: Market price (Rs) | B11: =Inputs!B13 -> 1836
A14: Infosys (two-stage DDM)
A15: r \ g2 | B15: =Inputs!$C$31+(-0.015) -> 0.04 | C15: =Inputs!$C$31+(-0.01) -> 0.045 | D15: =Inputs!$C$31+(-0.005) -> 0.05 | E15: =Inputs!$C$31+(0) -> 0.055 | F15: =Inputs!$C$31+(0.005) -> 0.06
A16: =Inputs!$C$15+(-0.02) -> 0.09333288 | B16: =IF(B$15<$A16,Inputs!$C$20*(1+Inputs!$C$27)/($A16-Inputs!$C$27)*(1-((1+Inputs!$C$27)/(1+$A16))^Inputs!$C$26)+Inputs!$C$20*(1+Inputs!$C$27)^Inputs!$C$26*(1+B$15)/(($A16-B$15)*(1+$A16)^Inputs!$C$26),"") -> 1111.6726 | C16: =IF(C$15<$A16,Inputs!$C$20*(1+Inputs!$C$27)/($A16-Inputs!$C$27)*(1-((1+Inputs!$C$27)/(1+$A16))^Inputs!$C$26)+Inputs!$C$20*(1+Inputs!$C$27)^Inputs!$C$26*(1+C$15)/(($A16-C$15)*(1+$A16)^Inputs!$C$26),"") -> 1207.4102 | D16: =IF(D$15<$A16,Inputs!$C$20*(1+Inputs!$C$27)/($A16-Inputs!$C$27)*(1-((1+Inputs!$C$27)/(1+$A16))^Inputs!$C$26)+Inputs!$C$20*(1+Inputs!$C$27)^Inputs!$C$26*(1+D$15)/(($A16-D$15)*(1+$A16)^Inputs!$C$26),"") -> 1325.2414 | E16: =IF(E$15<$A16,Inputs!$C$20*(1+Inputs!$C$27)/($A16-Inputs!$C$27)*(1-((1+Inputs!$C$27)/(1+$A16))^Inputs!$C$26)+Inputs!$C$20*(1+Inputs!$C$27)^Inputs!$C$26*(1+E$15)/(($A16-E$15)*(1+$A16)^Inputs!$C$26),"") -> 1473.8114 | F16: =IF(F$15<$A16,Inputs!$C$20*(1+Inputs!$C$27)/($A16-Inputs!$C$27)*(1-((1+Inputs!$C$27)/(1+$A16))^Inputs!$C$26)+Inputs!$C$20*(1+Inputs!$C$27)^Inputs!$C$26*(1+F$15)/(($A16-F$15)*(1+$A16)^Inputs!$C$26),"") -> 1666.9532
A17: =Inputs!$C$15+(-0.01) -> 0.10333288 | B17: =IF(B$15<$A17,Inputs!$C$20*(1+Inputs!$C$27)/($A17-Inputs!$C$27)*(1-((1+Inputs!$C$27)/(1+$A17))^Inputs!$C$26)+Inputs!$C$20*(1+Inputs!$C$27)^Inputs!$C$26*(1+B$15)/(($A17-B$15)*(1+$A17)^Inputs!$C$26),"") -> 933.51923 | C17: =IF(C$15<$A17,Inputs!$C$20*(1+Inputs!$C$27)/($A17-Inputs!$C$27)*(1-((1+Inputs!$C$27)/(1+$A17))^Inputs!$C$26)+Inputs!$C$20*(1+Inputs!$C$27)^Inputs!$C$26*(1+C$15)/(($A17-C$15)*(1+$A17)^Inputs!$C$26),"") -> 997.93039 | D17: =IF(D$15<$A17,Inputs!$C$20*(1+Inputs!$C$27)/($A17-Inputs!$C$27)*(1-((1+Inputs!$C$27)/(1+$A17))^Inputs!$C$26)+Inputs!$C$20*(1+Inputs!$C$27)^Inputs!$C$26*(1+D$15)/(($A17-D$15)*(1+$A17)^Inputs!$C$26),"") -> 1074.4188 | E17: =IF(E$15<$A17,Inputs!$C$20*(1+Inputs!$C$27)/($A17-Inputs!$C$27)*(1-((1+Inputs!$C$27)/(1+$A17))^Inputs!$C$26)+Inputs!$C$20*(1+Inputs!$C$27)^Inputs!$C$26*(1+E$15)/(($A17-E$15)*(1+$A17)^Inputs!$C$26),"") -> 1166.7324 | F17: =IF(F$15<$A17,Inputs!$C$20*(1+Inputs!$C$27)/($A17-Inputs!$C$27)*(1-((1+Inputs!$C$27)/(1+$A17))^Inputs!$C$26)+Inputs!$C$20*(1+Inputs!$C$27)^Inputs!$C$26*(1+F$15)/(($A17-F$15)*(1+$A17)^Inputs!$C$26),"") -> 1280.3495
A18: =Inputs!$C$15+(0) -> 0.11333288 | B18: =IF(B$15<$A18,Inputs!$C$20*(1+Inputs!$C$27)/($A18-Inputs!$C$27)*(1-((1+Inputs!$C$27)/(1+$A18))^Inputs!$C$26)+Inputs!$C$20*(1+Inputs!$C$27)^Inputs!$C$26*(1+B$15)/(($A18-B$15)*(1+$A18)^Inputs!$C$26),"") -> 804.03377 | C18: =IF(C$15<$A18,Inputs!$C$20*(1+Inputs!$C$27)/($A18-Inputs!$C$27)*(1-((1+Inputs!$C$27)/(1+$A18))^Inputs!$C$26)+Inputs!$C$20*(1+Inputs!$C$27)^Inputs!$C$26*(1+C$15)/(($A18-C$15)*(1+$A18)^Inputs!$C$26),"") -> 849.83756 | D18: =IF(D$15<$A18,Inputs!$C$20*(1+Inputs!$C$27)/($A18-Inputs!$C$27)*(1-((1+Inputs!$C$27)/(1+$A18))^Inputs!$C$26)+Inputs!$C$20*(1+Inputs!$C$27)^Inputs!$C$26*(1+D$15)/(($A18-D$15)*(1+$A18)^Inputs!$C$26),"") -> 902.87358 | E18: =IF(E$15<$A18,Inputs!$C$20*(1+Inputs!$C$27)/($A18-Inputs!$C$27)*(1-((1+Inputs!$C$27)/(1+$A18))^Inputs!$C$26)+Inputs!$C$20*(1+Inputs!$C$27)^Inputs!$C$26*(1+E$15)/(($A18-E$15)*(1+$A18)^Inputs!$C$26),"") -> 965.00155 | F18: =IF(F$15<$A18,Inputs!$C$20*(1+Inputs!$C$27)/($A18-Inputs!$C$27)*(1-((1+Inputs!$C$27)/(1+$A18))^Inputs!$C$26)+Inputs!$C$20*(1+Inputs!$C$27)^Inputs!$C$26*(1+F$15)/(($A18-F$15)*(1+$A18)^Inputs!$C$26),"") -> 1038.7786
A19: =Inputs!$C$15+(0.01) -> 0.12333288 | B19: =IF(B$15<$A19,Inputs!$C$20*(1+Inputs!$C$27)/($A19-Inputs!$C$27)*(1-((1+Inputs!$C$27)/(1+$A19))^Inputs!$C$26)+Inputs!$C$20*(1+Inputs!$C$27)^Inputs!$C$26*(1+B$15)/(($A19-B$15)*(1+$A19)^Inputs!$C$26),"") -> 705.69238 | C19: =IF(C$15<$A19,Inputs!$C$20*(1+Inputs!$C$27)/($A19-Inputs!$C$27)*(1-((1+Inputs!$C$27)/(1+$A19))^Inputs!$C$26)+Inputs!$C$20*(1+Inputs!$C$27)^Inputs!$C$26*(1+C$15)/(($A19-C$15)*(1+$A19)^Inputs!$C$26),"") -> 739.61861 | D19: =IF(D$15<$A19,Inputs!$C$20*(1+Inputs!$C$27)/($A19-Inputs!$C$27)*(1-((1+Inputs!$C$27)/(1+$A19))^Inputs!$C$26)+Inputs!$C$20*(1+Inputs!$C$27)^Inputs!$C$26*(1+D$15)/(($A19-D$15)*(1+$A19)^Inputs!$C$26),"") -> 778.17118 | E19: =IF(E$15<$A19,Inputs!$C$20*(1+Inputs!$C$27)/($A19-Inputs!$C$27)*(1-((1+Inputs!$C$27)/(1+$A19))^Inputs!$C$26)+Inputs!$C$20*(1+Inputs!$C$27)^Inputs!$C$26*(1+E$15)/(($A19-E$15)*(1+$A19)^Inputs!$C$26),"") -> 822.36562 | F19: =IF(F$15<$A19,Inputs!$C$20*(1+Inputs!$C$27)/($A19-Inputs!$C$27)*(1-((1+Inputs!$C$27)/(1+$A19))^Inputs!$C$26)+Inputs!$C$20*(1+Inputs!$C$27)^Inputs!$C$26*(1+F$15)/(($A19-F$15)*(1+$A19)^Inputs!$C$26),"") -> 873.53819
A20: =Inputs!$C$15+(0.02) -> 0.13333288 | B20: =IF(B$15<$A20,Inputs!$C$20*(1+Inputs!$C$27)/($A20-Inputs!$C$27)*(1-((1+Inputs!$C$27)/(1+$A20))^Inputs!$C$26)+Inputs!$C$20*(1+Inputs!$C$27)^Inputs!$C$26*(1+B$15)/(($A20-B$15)*(1+$A20)^Inputs!$C$26),"") -> 628.48168 | C20: =IF(C$15<$A20,Inputs!$C$20*(1+Inputs!$C$27)/($A20-Inputs!$C$27)*(1-((1+Inputs!$C$27)/(1+$A20))^Inputs!$C$26)+Inputs!$C$20*(1+Inputs!$C$27)^Inputs!$C$26*(1+C$15)/(($A20-C$15)*(1+$A20)^Inputs!$C$26),"") -> 654.40813 | D20: =IF(D$15<$A20,Inputs!$C$20*(1+Inputs!$C$27)/($A20-Inputs!$C$27)*(1-((1+Inputs!$C$27)/(1+$A20))^Inputs!$C$26)+Inputs!$C$20*(1+Inputs!$C$27)^Inputs!$C$26*(1+D$15)/(($A20-D$15)*(1+$A20)^Inputs!$C$26),"") -> 683.44577 | E20: =IF(E$15<$A20,Inputs!$C$20*(1+Inputs!$C$27)/($A20-Inputs!$C$27)*(1-((1+Inputs!$C$27)/(1+$A20))^Inputs!$C$26)+Inputs!$C$20*(1+Inputs!$C$27)^Inputs!$C$26*(1+E$15)/(($A20-E$15)*(1+$A20)^Inputs!$C$26),"") -> 716.19036 | F20: =IF(F$15<$A20,Inputs!$C$20*(1+Inputs!$C$27)/($A20-Inputs!$C$27)*(1-((1+Inputs!$C$27)/(1+$A20))^Inputs!$C$26)+Inputs!$C$20*(1+Inputs!$C$27)^Inputs!$C$26*(1+F$15)/(($A20-F$15)*(1+$A20)^Inputs!$C$26),"") -> 753.40015
A21: Market price (Rs) | B21: =Inputs!C13 -> 1035
A24: ICICI Bank (two-stage P/B)
A25: r \ g2 | B25: =Inputs!$D$31+(-0.015) -> 0.04 | C25: =Inputs!$D$31+(-0.01) -> 0.045 | D25: =Inputs!$D$31+(-0.005) -> 0.05 | E25: =Inputs!$D$31+(0) -> 0.055 | F25: =Inputs!$D$31+(0.005) -> 0.06
A26: =Inputs!$D$15+(-0.02) -> 0.12687792 | B26: =IF(B$25<$A26,Inputs!$D$29*Inputs!$D$28*Inputs!$D$22/($A26-Inputs!$D$28*(1-Inputs!$D$29))*(1-((1+Inputs!$D$28*(1-Inputs!$D$29))/(1+$A26))^Inputs!$D$26)+Inputs!$D$22*(1+Inputs!$D$28*(1-Inputs!$D$29))^Inputs!$D$26*(Inputs!$D$30-B$25)/($A26-B$25)/(1+$A26)^Inputs!$D$26,"") -> 750.49318 | C26: =IF(C$25<$A26,Inputs!$D$29*Inputs!$D$28*Inputs!$D$22/($A26-Inputs!$D$28*(1-Inputs!$D$29))*(1-((1+Inputs!$D$28*(1-Inputs!$D$29))/(1+$A26))^Inputs!$D$26)+Inputs!$D$22*(1+Inputs!$D$28*(1-Inputs!$D$29))^Inputs!$D$26*(Inputs!$D$30-C$25)/($A26-C$25)/(1+$A26)^Inputs!$D$26,"") -> 759.34796 | D26: =IF(D$25<$A26,Inputs!$D$29*Inputs!$D$28*Inputs!$D$22/($A26-Inputs!$D$28*(1-Inputs!$D$29))*(1-((1+Inputs!$D$28*(1-Inputs!$D$29))/(1+$A26))^Inputs!$D$26)+Inputs!$D$22*(1+Inputs!$D$28*(1-Inputs!$D$29))^Inputs!$D$26*(Inputs!$D$30-D$25)/($A26-D$25)/(1+$A26)^Inputs!$D$26,"") -> 769.35455 | E26: =IF(E$25<$A26,Inputs!$D$29*Inputs!$D$28*Inputs!$D$22/($A26-Inputs!$D$28*(1-Inputs!$D$29))*(1-((1+Inputs!$D$28*(1-Inputs!$D$29))/(1+$A26))^Inputs!$D$26)+Inputs!$D$22*(1+Inputs!$D$28*(1-Inputs!$D$29))^Inputs!$D$26*(Inputs!$D$30-E$25)/($A26-E$25)/(1+$A26)^Inputs!$D$26,"") -> 780.75329 | F26: =IF(F$25<$A26,Inputs!$D$29*Inputs!$D$28*Inputs!$D$22/($A26-Inputs!$D$28*(1-Inputs!$D$29))*(1-((1+Inputs!$D$28*(1-Inputs!$D$29))/(1+$A26))^Inputs!$D$26)+Inputs!$D$22*(1+Inputs!$D$28*(1-Inputs!$D$29))^Inputs!$D$26*(Inputs!$D$30-F$25)/($A26-F$25)/(1+$A26)^Inputs!$D$26,"") -> 793.85645
A27: =Inputs!$D$15+(-0.01) -> 0.13687792 | B27: =IF(B$25<$A27,Inputs!$D$29*Inputs!$D$28*Inputs!$D$22/($A27-Inputs!$D$28*(1-Inputs!$D$29))*(1-((1+Inputs!$D$28*(1-Inputs!$D$29))/(1+$A27))^Inputs!$D$26)+Inputs!$D$22*(1+Inputs!$D$28*(1-Inputs!$D$29))^Inputs!$D$26*(Inputs!$D$30-B$25)/($A27-B$25)/(1+$A27)^Inputs!$D$26,"") -> 650.96555 | C27: =IF(C$25<$A27,Inputs!$D$29*Inputs!$D$28*Inputs!$D$22/($A27-Inputs!$D$28*(1-Inputs!$D$29))*(1-((1+Inputs!$D$28*(1-Inputs!$D$29))/(1+$A27))^Inputs!$D$26)+Inputs!$D$22*(1+Inputs!$D$28*(1-Inputs!$D$29))^Inputs!$D$26*(Inputs!$D$30-C$25)/($A27-C$25)/(1+$A27)^Inputs!$D$26,"") -> 654.80801 | D27: =IF(D$25<$A27,Inputs!$D$29*Inputs!$D$28*Inputs!$D$22/($A27-Inputs!$D$28*(1-Inputs!$D$29))*(1-((1+Inputs!$D$28*(1-Inputs!$D$29))/(1+$A27))^Inputs!$D$26)+Inputs!$D$22*(1+Inputs!$D$28*(1-Inputs!$D$29))^Inputs!$D$26*(Inputs!$D$30-D$25)/($A27-D$25)/(1+$A27)^Inputs!$D$26,"") -> 659.09275 | E27: =IF(E$25<$A27,Inputs!$D$29*Inputs!$D$28*Inputs!$D$22/($A27-Inputs!$D$28*(1-Inputs!$D$29))*(1-((1+Inputs!$D$28*(1-Inputs!$D$29))/(1+$A27))^Inputs!$D$26)+Inputs!$D$22*(1+Inputs!$D$28*(1-Inputs!$D$29))^Inputs!$D$26*(Inputs!$D$30-E$25)/($A27-E$25)/(1+$A27)^Inputs!$D$26,"") -> 663.90081 | F27: =IF(F$25<$A27,Inputs!$D$29*Inputs!$D$28*Inputs!$D$22/($A27-Inputs!$D$28*(1-Inputs!$D$29))*(1-((1+Inputs!$D$28*(1-Inputs!$D$29))/(1+$A27))^Inputs!$D$26)+Inputs!$D$22*(1+Inputs!$D$28*(1-Inputs!$D$29))^Inputs!$D$26*(Inputs!$D$30-F$25)/($A27-F$25)/(1+$A27)^Inputs!$D$26,"") -> 669.33427
A28: =Inputs!$D$15+(0) -> 0.14687792 | B28: =IF(B$25<$A28,Inputs!$D$29*Inputs!$D$28*Inputs!$D$22/($A28-Inputs!$D$28*(1-Inputs!$D$29))*(1-((1+Inputs!$D$28*(1-Inputs!$D$29))/(1+$A28))^Inputs!$D$26)+Inputs!$D$22*(1+Inputs!$D$28*(1-Inputs!$D$29))^Inputs!$D$26*(Inputs!$D$30-B$25)/($A28-B$25)/(1+$A28)^Inputs!$D$26,"") -> 571.07471 | C28: =IF(C$25<$A28,Inputs!$D$29*Inputs!$D$28*Inputs!$D$22/($A28-Inputs!$D$28*(1-Inputs!$D$29))*(1-((1+Inputs!$D$28*(1-Inputs!$D$29))/(1+$A28))^Inputs!$D$26)+Inputs!$D$22*(1+Inputs!$D$28*(1-Inputs!$D$29))^Inputs!$D$26*(Inputs!$D$30-C$25)/($A28-C$25)/(1+$A28)^Inputs!$D$26,"") -> 571.79003 | D28: =IF(D$25<$A28,Inputs!$D$29*Inputs!$D$28*Inputs!$D$22/($A28-Inputs!$D$28*(1-Inputs!$D$29))*(1-((1+Inputs!$D$28*(1-Inputs!$D$29))/(1+$A28))^Inputs!$D$26)+Inputs!$D$22*(1+Inputs!$D$28*(1-Inputs!$D$29))^Inputs!$D$26*(Inputs!$D$30-D$25)/($A28-D$25)/(1+$A28)^Inputs!$D$26,"") -> 572.57919 | E28: =IF(E$25<$A28,Inputs!$D$29*Inputs!$D$28*Inputs!$D$22/($A28-Inputs!$D$28*(1-Inputs!$D$29))*(1-((1+Inputs!$D$28*(1-Inputs!$D$29))/(1+$A28))^Inputs!$D$26)+Inputs!$D$22*(1+Inputs!$D$28*(1-Inputs!$D$29))^Inputs!$D$26*(Inputs!$D$30-E$25)/($A28-E$25)/(1+$A28)^Inputs!$D$26,"") -> 573.45424 | F28: =IF(F$25<$A28,Inputs!$D$29*Inputs!$D$28*Inputs!$D$22/($A28-Inputs!$D$28*(1-Inputs!$D$29))*(1-((1+Inputs!$D$28*(1-Inputs!$D$29))/(1+$A28))^Inputs!$D$26)+Inputs!$D$22*(1+Inputs!$D$28*(1-Inputs!$D$29))^Inputs!$D$26*(Inputs!$D$30-F$25)/($A28-F$25)/(1+$A28)^Inputs!$D$26,"") -> 574.43002
A29: =Inputs!$D$15+(0.01) -> 0.15687792 | B29: =IF(B$25<$A29,Inputs!$D$29*Inputs!$D$28*Inputs!$D$22/($A29-Inputs!$D$28*(1-Inputs!$D$29))*(1-((1+Inputs!$D$28*(1-Inputs!$D$29))/(1+$A29))^Inputs!$D$26)+Inputs!$D$22*(1+Inputs!$D$28*(1-Inputs!$D$29))^Inputs!$D$26*(Inputs!$D$30-B$25)/($A29-B$25)/(1+$A29)^Inputs!$D$26,"") -> 505.7257 | C29: =IF(C$25<$A29,Inputs!$D$29*Inputs!$D$28*Inputs!$D$22/($A29-Inputs!$D$28*(1-Inputs!$D$29))*(1-((1+Inputs!$D$28*(1-Inputs!$D$29))/(1+$A29))^Inputs!$D$26)+Inputs!$D$22*(1+Inputs!$D$28*(1-Inputs!$D$29))^Inputs!$D$26*(Inputs!$D$30-C$25)/($A29-C$25)/(1+$A29)^Inputs!$D$26,"") -> 504.46922 | D29: =IF(D$25<$A29,Inputs!$D$29*Inputs!$D$28*Inputs!$D$22/($A29-Inputs!$D$28*(1-Inputs!$D$29))*(1-((1+Inputs!$D$28*(1-Inputs!$D$29))/(1+$A29))^Inputs!$D$26)+Inputs!$D$22*(1+Inputs!$D$28*(1-Inputs!$D$29))^Inputs!$D$26*(Inputs!$D$30-D$25)/($A29-D$25)/(1+$A29)^Inputs!$D$26,"") -> 503.09518 | E29: =IF(E$25<$A29,Inputs!$D$29*Inputs!$D$28*Inputs!$D$22/($A29-Inputs!$D$28*(1-Inputs!$D$29))*(1-((1+Inputs!$D$28*(1-Inputs!$D$29))/(1+$A29))^Inputs!$D$26)+Inputs!$D$22*(1+Inputs!$D$28*(1-Inputs!$D$29))^Inputs!$D$26*(Inputs!$D$30-E$25)/($A29-E$25)/(1+$A29)^Inputs!$D$26,"") -> 501.58627 | F29: =IF(F$25<$A29,Inputs!$D$29*Inputs!$D$28*Inputs!$D$22/($A29-Inputs!$D$28*(1-Inputs!$D$29))*(1-((1+Inputs!$D$28*(1-Inputs!$D$29))/(1+$A29))^Inputs!$D$26)+Inputs!$D$22*(1+Inputs!$D$28*(1-Inputs!$D$29))^Inputs!$D$26*(Inputs!$D$30-F$25)/($A29-F$25)/(1+$A29)^Inputs!$D$26,"") -> 499.92161
A30: =Inputs!$D$15+(0.02) -> 0.16687792 | B30: =IF(B$25<$A30,Inputs!$D$29*Inputs!$D$28*Inputs!$D$22/($A30-Inputs!$D$28*(1-Inputs!$D$29))*(1-((1+Inputs!$D$28*(1-Inputs!$D$29))/(1+$A30))^Inputs!$D$26)+Inputs!$D$22*(1+Inputs!$D$28*(1-Inputs!$D$29))^Inputs!$D$26*(Inputs!$D$30-B$25)/($A30-B$25)/(1+$A30)^Inputs!$D$26,"") -> 451.4332 | C30: =IF(C$25<$A30,Inputs!$D$29*Inputs!$D$28*Inputs!$D$22/($A30-Inputs!$D$28*(1-Inputs!$D$29))*(1-((1+Inputs!$D$28*(1-Inputs!$D$29))/(1+$A30))^Inputs!$D$26)+Inputs!$D$22*(1+Inputs!$D$28*(1-Inputs!$D$29))^Inputs!$D$26*(Inputs!$D$30-C$25)/($A30-C$25)/(1+$A30)^Inputs!$D$26,"") -> 448.93577 | D30: =IF(D$25<$A30,Inputs!$D$29*Inputs!$D$28*Inputs!$D$22/($A30-Inputs!$D$28*(1-Inputs!$D$29))*(1-((1+Inputs!$D$28*(1-Inputs!$D$29))/(1+$A30))^Inputs!$D$26)+Inputs!$D$22*(1+Inputs!$D$28*(1-Inputs!$D$29))^Inputs!$D$26*(Inputs!$D$30-D$25)/($A30-D$25)/(1+$A30)^Inputs!$D$26,"") -> 446.22467 | E30: =IF(E$25<$A30,Inputs!$D$29*Inputs!$D$28*Inputs!$D$22/($A30-Inputs!$D$28*(1-Inputs!$D$29))*(1-((1+Inputs!$D$28*(1-Inputs!$D$29))/(1+$A30))^Inputs!$D$26)+Inputs!$D$22*(1+Inputs!$D$28*(1-Inputs!$D$29))^Inputs!$D$26*(Inputs!$D$30-E$25)/($A30-E$25)/(1+$A30)^Inputs!$D$26,"") -> 443.27124 | F30: =IF(F$25<$A30,Inputs!$D$29*Inputs!$D$28*Inputs!$D$22/($A30-Inputs!$D$28*(1-Inputs!$D$29))*(1-((1+Inputs!$D$28*(1-Inputs!$D$29))/(1+$A30))^Inputs!$D$26)+Inputs!$D$22*(1+Inputs!$D$28*(1-Inputs!$D$29))^Inputs!$D$26*(Inputs!$D$30-F$25)/($A30-F$25)/(1+$A30)^Inputs!$D$26,"") -> 440.04147
A31: Market price (Rs) | B31: =Inputs!D13 -> 1310.6

Sheet Summary
A1: ticker | B1: name | C1: model | D1: price | E1: cost_of_equity | F1: intrinsic_value | G1: model_upside | H1: comps_value | I1: comps_upside | J1: blended_value | K1: blended_upside | L1: market_implied_growth | M1: verdict
A2: =Inputs!B11 -> HINDUNILVR.NS | B2: =Inputs!B10 -> Hindustan Unilever | C2: =Inputs!B12 -> Two-stage DDM | D2: =Inputs!B13 -> 1836 | E2: =Inputs!B15 -> 0.09770732 | F2: =DDM!B29 -> 1081.2815 | G2: =F2/D2-1 -> -0.4110667 | H2: =Comps!B11 -> 2075.4783 | I2: =H2/D2-1 -> 0.13043478 | J2: =AVERAGE(F2,H2) -> 1578.3799 | K2: =J2/D2-1 -> -0.14031596 | L2: =DDM!B33 -> 0.073729696 | M2: =IF(K2>Inputs!$B$7,"Undervalued",IF(K2<-Inputs!$B$7,"Overvalued","Fairly valued")) -> Fairly valued
A3: =Inputs!C11 -> INFY.NS | B3: =Inputs!C10 -> Infosys | C3: =Inputs!C12 -> Two-stage DDM | D3: =Inputs!C13 -> 1035 | E3: =Inputs!C15 -> 0.11333288 | F3: =DDM!C29 -> 965.00155 | G3: =F3/D3-1 -> -0.067631348 | H3: =Comps!B20 -> 1073.3333 | I3: =H3/D3-1 -> 0.037037037 | J3: =AVERAGE(F3,H3) -> 1019.1674 | K3: =J3/D3-1 -> -0.015297156 | L3: =DDM!C33 -> 0.063988486 | M3: =IF(K3>Inputs!$B$7,"Undervalued",IF(K3<-Inputs!$B$7,"Overvalued","Fairly valued")) -> Fairly valued
A4: =Inputs!D11 -> ICICIBANK.NS | B4: =Inputs!D10 -> ICICI Bank | C4: =Inputs!D12 -> Two-stage P/B (residual income) | D4: =Inputs!D13 -> 1310.6 | E4: =Inputs!D15 -> 0.14687792 | F4: =Bank!B32 -> 573.45424 | G4: =F4/D4-1 -> -0.56244908 | H4: =Comps!B31 -> 1139.0413 | I4: =H4/D4-1 -> -0.13090085 | J4: =AVERAGE(F4,H4) -> 856.24779 | K4: =J4/D4-1 -> -0.34667496 | L4: =Bank!B37 -> 0.13872537 | M4: =IF(K4>Inputs!$B$7,"Undervalued",IF(K4<-Inputs!$B$7,"Overvalued","Fairly valued")) -> Overvalued
